setup.py
s3ninja/__init__.py
s3ninja/main.py
s3ninja.egg-info/PKG-INFO
s3ninja.egg-info/SOURCES.txt
s3ninja.egg-info/dependency_links.txt
s3ninja.egg-info/entry_points.txt
s3ninja.egg-info/not-zip-safe
s3ninja.egg-info/requires.txt
s3ninja.egg-info/top_level.txt